{
  "uid": "e8a5438d2f14ddc1",
  "content_type": "instapaper",
  "source": "instapaper://private-content/1757710870",
  "title": "💥Putting in Musk-ian Hours💥",
  "status": "success",
  "date": "2025-08-05T13:28:47.086824",
  "error": null,
  "content_path": "output/articles/markdown/e8a5438d2f14ddc1.md",
  "html_path": "output/articles/html/e8a5438d2f14ddc1.html",
  "audio_path": null,
  "transcript_path": null,
  "tags": [],
  "notes": [],
  "fetch_method": "instapaper_api",
  "fetch_details": {
    "attempts": [],
    "successful_method": "instapaper_api",
    "is_truncated": false,
    "total_attempts": 1,
    "fetch_time": null
  },
  "category_version": null,
  "last_tagged_at": null,
  "source_hash": "990967f7b980f0976098e44f1d04b5b5",
  "type_specific": {
    "bookmark_id": 1757710870,
    "instapaper_time": 1740932182,
    "starred": true,
    "progress": 0.0,
    "folders": [
      "Unread",
      "Archive",
      "Starred"
    ],
    "is_private_content": true,
    "private_source": "email"
  },
  "video_id": null,
  "created_at": "2025-08-05T13:28:47.087666",
  "updated_at": "2025-08-05T13:28:47.087681"
}