{
  "uid": "073ab9c663f84ad9",
  "content_type": "private_content",
  "source": "instapaper-private://email/28b79cb7733bd26dd38a7f794c6e331c/",
  "title": "Substack Raises Series A, An Interview With Substack Co-Founders Christopher Best and Hamish McKenzie (Stratechery Daily Update 7-17-2019)",
  "status": "converted_from_csv",
  "date": "2019-07-17T00:49:07",
  "error": null,
  "content_path": "output/articles/markdown/073ab9c663f84ad9.md",
  "html_path": "output/articles/html/073ab9c663f84ad9.html",
  "audio_path": null,
  "transcript_path": null,
  "tags": [],
  "notes": [],
  "fetch_method": "csv_export",
  "fetch_details": {
    "source": "instapaper_csv_export",
    "csv_row": 3083,
    "selection": ""
  },
  "category_version": null,
  "last_tagged_at": null,
  "source_hash": "b498d664360ddf334f60b9e5512638fb",
  "type_specific": {
    "folder": "Unread",
    "instapaper_timestamp": "1563349747",
    "is_private_content": true,
    "private_source": "instapaper_email",
    "selection": ""
  },
  "video_id": null,
  "created_at": "2019-07-17T00:49:07",
  "updated_at": "2019-07-17T00:49:07"
}