{
  "uid": "0cd3ba608ac52eae",
  "content_type": "web_bookmark",
  "source": "https://www.nytimes.com/2017/10/31/business/too-many-restaurants-wall-street.html",
  "title": "Thanks to Wall St., There May Be Too Many Restaurants - The New York Times",
  "status": "converted_from_csv",
  "date": "2017-10-31T12:06:47",
  "error": null,
  "content_path": "output/articles/markdown/0cd3ba608ac52eae.md",
  "html_path": "output/articles/html/0cd3ba608ac52eae.html",
  "audio_path": null,
  "transcript_path": null,
  "tags": [],
  "notes": [],
  "fetch_method": "csv_export",
  "fetch_details": {
    "source": "instapaper_csv_export",
    "csv_row": 3736,
    "selection": ""
  },
  "category_version": null,
  "last_tagged_at": null,
  "source_hash": "1df162f1a640cc902af97b2175adaffc",
  "type_specific": {
    "folder": "Unread",
    "instapaper_timestamp": "1509476807",
    "is_private_content": false,
    "private_source": "",
    "selection": ""
  },
  "video_id": null,
  "created_at": "2017-10-31T12:06:47",
  "updated_at": "2017-10-31T12:06:47"
}