{
  "uid": "548e02067ee14276",
  "content_type": "private_content",
  "source": "instapaper-private://email/a22318022ecdc5cb645264ae63ecf893/",
  "title": "Is Another Financial Crisis Coming? Interview With Wealthion",
  "status": "converted_from_csv",
  "date": "2021-07-14T11:26:00",
  "error": null,
  "content_path": "output/articles/markdown/548e02067ee14276.md",
  "html_path": "output/articles/html/548e02067ee14276.html",
  "audio_path": null,
  "transcript_path": null,
  "tags": [],
  "notes": [],
  "fetch_method": "csv_export",
  "fetch_details": {
    "source": "instapaper_csv_export",
    "csv_row": 2100,
    "selection": ""
  },
  "category_version": null,
  "last_tagged_at": null,
  "source_hash": "e15b5093081c9192f0e2025c723f34b4",
  "type_specific": {
    "folder": "Unread",
    "instapaper_timestamp": "1626287160",
    "is_private_content": true,
    "private_source": "instapaper_email",
    "selection": ""
  },
  "video_id": null,
  "created_at": "2021-07-14T11:26:00",
  "updated_at": "2021-07-14T11:26:00"
}