{
  "uid": "5df47ce11b37970c",
  "content_type": "private_content",
  "source": "instapaper-private://email/019e12effc64db9a9c35ce6fdde2aaeb/",
  "title": "🔥BigLaw on BigLaw Violence🔥",
  "status": "converted_from_csv",
  "date": "2024-04-09T05:04:29",
  "error": null,
  "content_path": "output/articles/markdown/5df47ce11b37970c.md",
  "html_path": "output/articles/html/5df47ce11b37970c.html",
  "audio_path": null,
  "transcript_path": null,
  "tags": [],
  "notes": [],
  "fetch_method": "csv_export",
  "fetch_details": {
    "source": "instapaper_csv_export",
    "csv_row": 320,
    "selection": ""
  },
  "category_version": null,
  "last_tagged_at": null,
  "source_hash": "8a7e231a3427144c086342ab8cf36bfd",
  "type_specific": {
    "folder": "Unread",
    "instapaper_timestamp": "1712664269",
    "is_private_content": true,
    "private_source": "instapaper_email",
    "selection": ""
  },
  "video_id": null,
  "created_at": "2024-04-09T05:04:29",
  "updated_at": "2024-04-09T05:04:29"
}