{
  "uid": "a3fd075680bdce04",
  "content_type": "web_bookmark",
  "source": "http://www.nytimes.com/2010/12/11/education/11education.html?pagewanted=print",
  "title": "Students Know Good Teaching When They Get It, Survey Finds - NYTimes.com",
  "status": "converted_from_csv",
  "date": "2010-12-21T21:04:58",
  "error": null,
  "content_path": "output/articles/markdown/a3fd075680bdce04.md",
  "html_path": "output/articles/html/a3fd075680bdce04.html",
  "audio_path": null,
  "transcript_path": null,
  "tags": [],
  "notes": [],
  "fetch_method": "csv_export",
  "fetch_details": {
    "source": "instapaper_csv_export",
    "csv_row": 6039,
    "selection": ""
  },
  "category_version": null,
  "last_tagged_at": null,
  "source_hash": "fb4a4272db434b346d2d9cfdf2e5854f",
  "type_specific": {
    "folder": "Archive",
    "instapaper_timestamp": "1292994298",
    "is_private_content": false,
    "private_source": "",
    "selection": ""
  },
  "video_id": null,
  "created_at": "2010-12-21T21:04:58",
  "updated_at": "2010-12-21T21:04:58"
}