{
  "uid": "f316db2c3bca60e4",
  "content_type": "web_bookmark",
  "source": "http://www.thedailybeast.com/articles/2016/03/05/the-secret-world-of-gamblers-betting-millions-on-the-2016-election.html",
  "title": "The Secret World of Gamblers Betting Millions on the 2016 Election",
  "status": "converted_from_csv",
  "date": "2016-03-14T10:03:21",
  "error": null,
  "content_path": "output/articles/markdown/f316db2c3bca60e4.md",
  "html_path": "output/articles/html/f316db2c3bca60e4.html",
  "audio_path": null,
  "transcript_path": null,
  "tags": [],
  "notes": [],
  "fetch_method": "csv_export",
  "fetch_details": {
    "source": "instapaper_csv_export",
    "csv_row": 4544,
    "selection": ""
  },
  "category_version": null,
  "last_tagged_at": null,
  "source_hash": "ed1fbf36644268e54d2d0ade97878067",
  "type_specific": {
    "folder": "Unread",
    "instapaper_timestamp": "1457975001",
    "is_private_content": false,
    "private_source": "",
    "selection": ""
  },
  "video_id": null,
  "created_at": "2016-03-14T10:03:21",
  "updated_at": "2016-03-14T10:03:21"
}